{
  "account": 4,
  "alarm": 32,
  "alarm-plus": 36,
  "alert": 38,
  "alert-circle": 40,
  "alert-octagon": 41,
  "arrange-bring-forward": 61,
  "arrange-bring-to-front": 62,
  "arrange-send-backward": 63,
  "arrange-send-to-back": 64,
  "arrow-down": 69,
  "arrow-down-circle": 3291,
  "arrow-left": 77,
  "arrow-left-circle": 3293,
  "arrow-right": 84,
  "arrow-right-circle": 3295,
  "arrow-up": 93,
  "arrow-up-circle": 3297,
  "bank": 112,
  "bell": 154,
  "bell-off": 155,
  "bluetooth": 175,
  "book": 186,
  "book-multiple": 187,
  "book-plus": 1499,
  "bookmark": 192,
  "border-all": 199,
  "border-bottom": 200,
  "border-horizontal": 202,
  "border-inside": 203,
  "border-left": 204,
  "border-none": 205,
  "border-outside": 206,
  "border-right": 207,
  "border-top": 209,
  "border-vertical": 210,
  "briefcase": 214,
  "calendar": 237,
  "camcorder": 252,
  "camera": 256,
  "cancel": 1850,
  "cart": 272,
  "chart-areaspline": 295,
  "chart-bar": 296,
  "chart-histogram": 297,
  "chart-line": 298,
  "chart-pie": 299,
  "check": 300,
  "chevron-double-down": 316,
  "chevron-double-left": 317,
  "chevron-double-right": 318,
  "chevron-double-up": 319,
  "chevron-down": 320,
  "chevron-left": 321,
  "chevron-right": 322,
  "chevron-up": 323,
  "circle": 1893,
  "clipboard": 327,
  "clipboard-check": 334,
  "clipboard-plus": 1873,
  "clipboard-text": 333,
  "clock": 2388,
  "closed-caption": 350,
  "cloud": 351,
  "cloud-download": 354,
  "cloud-upload": 359,
  "comment": 378,
  "comment-alert": 381,
  "comment-text": 392,
  "console": 397,
  "content-cut": 400,
  "content-duplicate": 401,
  "content-paste": 402,
  "content-save": 403,
  "content-save-all": 404,
  "credit-card": 4079,
  "credit-card-scan": 4084,
  "crop": 414,
  "crop-free": 415,
  "currency-eur": 429,
  "currency-gbp": 430,
  "currency-rub": 433,
  "currency-usd": 449,
  "delete": 436,
  "diamond-stone": 456,
  "dots-horizontal": 472,
  "dots-vertical": 473,
  "download": 474,
  "eject": 490,
  "email": 494,
  "email-open": 495,
  "eye": 520,
  "eye-off": 521,
  "factory": 527,
  "fast-forward": 529,
  "file": 532,
  "file-multiple": 546,
  "file-plus": 1874,
  "flag": 571,
  "flash": 577,
  "flask": 147,
  "flask-empty": 148,
  "folder": 587,
  "folder-multiple": 595,
  "folder-plus": 599,
  "format-align-bottom": 1875,
  "format-align-center": 608,
  "format-align-justify": 609,
  "format-align-left": 610,
  "format-align-middle": 1876,
  "format-align-right": 611,
  "format-align-top": 1877,
  "format-bold": 612,
  "format-clear": 613,
  "format-float-center": 615,
  "format-float-left": 616,
  "format-float-none": 617,
  "format-float-right": 618,
  "format-indent-decrease": 629,
  "format-indent-increase": 630,
  "format-italic": 631,
  "format-line-spacing": 632,
  "format-list-bulleted": 633,
  "format-list-checks": 1878,
  "format-quote-close": 638,
  "format-quote-open": 1879,
  "format-underline": 647,
  "format-wrap-inline": 648,
  "format-wrap-square": 649,
  "format-wrap-tight": 650,
  "format-wrap-top-bottom": 651,
  "forum": 652,
  "fullscreen": 659,
  "fullscreen-exit": 660,
  "gift": 3652,
  "grid": 705,
  "grid-large": 1880,
  "grid-off": 706,
  "group": 707,
  "hamburger": 1669,
  "heart": 721,
  "heart-half": 1759,
  "heart-off": 1881,
  "help": 726,
  "help-circle": 727,
  "hexagon": 728,
  "home": 732,
  "image": 745,
  "inbox": 1671,
  "information": 764,
  "label": 789,
  "layers": 808,
  "lightbulb": 821,
  "lightbulb-on": 1768,
  "link": 823,
  "link-variant": 825,
  "lock": 830,
  "lock-open": 831,
  "login": 834,
  "logout": 835,
  "magnify": 841,
  "magnify-minus": 842,
  "magnify-plus": 843,
  "map-marker": 846,
  "memory": 859,
  "menu": 860,
  "message": 865,
  "message-alert": 866,
  "message-image": 868,
  "message-processing": 870,
  "message-reply": 871,
  "message-text": 873,
  "message-video": 875,
  "microphone": 876,
  "microphone-off": 877,
  "minus": 884,
  "minus-box": 885,
  "minus-circle": 886,
  "monitor": 889,
  "monitor-multiple": 890,
  "music": 1882,
  "music-off": 1883,
  "nfc-variant": 920,
  "note": 922,
  "note-multiple": 1720,
  "note-plus": 924,
  "note-text": 926,
  "octagon": 963,
  "paperclip": 994,
  "pause": 996,
  "pencil": 1003,
  "phone": 1010,
  "pin": 1027,
  "pin-off": 1028,
  "play": 1034,
  "plus": 1045,
  "plus-box": 1046,
  "plus-circle": 1047,
  "power": 1061,
  "presentation": 1064,
  "presentation-play": 1065,
  "printer": 1066,
  "redo-variant": 1103,
  "refresh": 1104,
  "repeat": 1110,
  "repeat-off": 1111,
  "repeat-once": 1112,
  "rewind": 1119,
  "rhombus": 1803,
  "rss": 1131,
  "script": 3009,
  "shield": 1176,
  "shuffle": 1181,
  "signal": 1186,
  "sitemap": 1194,
  "skip-next": 1197,
  "skip-previous": 1198,
  "sleep": 1202,
  "sleep-off": 1203,
  "spellcheck": 1222,
  "square": 1892,
  "star": 1230,
  "star-half": 582,
  "stop": 1243,
  "tab": 1257,
  "tab-plus": 1884,
  "table": 1259,
  "taco": 1890,
  "tag": 1273,
  "television": 1282,
  "thumb-down": 1297,
  "thumb-up": 1299,
  "thumbs-up-down": 1301,
  "tooltip": 1315,
  "tooltip-text": 1320,
  "triangle": 1334,
  "trophy": 1336,
  "undo-variant": 1357,
  "unfold-less-horizontal": 1358,
  "unfold-less-vertical": 1888,
  "unfold-more-horizontal": 1359,
  "unfold-more-vertical": 1889,
  "ungroup": 1360,
  "upload": 1362,
  "vector-arrange-above": 1364,
  "vector-arrange-below": 1365,
  "vector-combine": 1368,
  "vector-difference": 1370,
  "vector-difference-ab": 1371,
  "vector-difference-ba": 1372,
  "vector-intersection": 1373,
  "vector-union": 1380,
  "view-dashboard": 1390,
  "view-module": 1395,
  "volume-high": 1406,
  "volume-minus": 1886,
  "volume-mute": 1887,
  "volume-off": 1409,
  "volume-plus": 1885,
  "wifi": 1449,
  "xml": 1472
}
